switchbot_utility/__init__.py
switchbot_utility/_version.py
switchbot_utility/battery_mixin.py
switchbot_utility/command_mixin.py
switchbot_utility/onoff_mixin.py
switchbot_utility/switchbot.py
switchbot_utility/switchbot_blind_tilt.py
switchbot_utility/switchbot_bot.py
switchbot_utility/switchbot_ceiling_light.py
switchbot_utility/switchbot_ceiling_light_pro.py
switchbot_utility/switchbot_color_bulb.py
switchbot_utility/switchbot_contact_sensor.py
switchbot_utility/switchbot_curtain.py
switchbot_utility/switchbot_device.py
switchbot_utility/switchbot_hub2.py
switchbot_utility/switchbot_humidifier.py
switchbot_utility/switchbot_ir_air_conditioner.py
switchbot_utility/switchbot_ir_device.py
switchbot_utility/switchbot_ir_dvd_speaker.py
switchbot_utility/switchbot_ir_fan.py
switchbot_utility/switchbot_ir_light.py
switchbot_utility/switchbot_ir_others.py
switchbot_utility/switchbot_ir_tv_ipstreamer_stb.py
switchbot_utility/switchbot_keypad.py
switchbot_utility/switchbot_keypad_touch.py
switchbot_utility/switchbot_lock.py
switchbot_utility/switchbot_meter.py
switchbot_utility/switchbot_meter_plus.py
switchbot_utility/switchbot_motion_sensor.py
switchbot_utility/switchbot_plug.py
switchbot_utility/switchbot_plug_mini_jp.py
switchbot_utility/switchbot_plug_mini_us.py
switchbot_utility/switchbot_robot_vacuum_cleaner_s1.py
switchbot_utility/switchbot_robot_vacuum_cleaner_s1_plus.py
switchbot_utility/switchbot_strip_light.py
switchbot_utility/switchbot_webhook.py
switchbot_utility-0.4.4.dist-info/METADATA
switchbot_utility-0.4.4.dist-info/WHEEL
switchbot_utility-0.4.4.dist-info/licenses/LICENSE
switchbot_utility-0.4.4.dist-info/RECORD
