Metadata-Version: 2.3
Name: switchbot_utility
Version: 0.4.4
Summary: Python Switchbot utilities
Project-URL: Homepage, https://github.com/iCarrot0605/Switchbot_utility
Project-URL: Bug Tracker, https://github.com/iCarrot0605/Switchbot_utility/issues
Author-email: MATSUMURA Hidetoshi <icarrot@mac.com>
Keywords: IoT,Switchbot,Switchbot API
Classifier: License :: OSI Approved :: MIT License
Classifier: Operating System :: OS Independent
Classifier: Programming Language :: Python :: 3
Requires-Python: >=3.6
Requires-Dist: requests
